alembic_utils_extended/__init__.py
alembic_utils_extended/depends.py
alembic_utils_extended/exceptions.py
alembic_utils_extended/experimental/__init__.py
alembic_utils_extended/experimental/_collect_instances.py
alembic_utils_extended/on_entity_mixin.py
alembic_utils_extended/pg_extension.py
alembic_utils_extended/pg_function.py
alembic_utils_extended/pg_grant_table.py
alembic_utils_extended/pg_materialized_view.py
alembic_utils_extended/pg_policy.py
alembic_utils_extended/pg_trigger.py
alembic_utils_extended/pg_view.py
alembic_utils_extended/py.typed
alembic_utils_extended/replaceable_entity.py
alembic_utils_extended/reversible_op.py
alembic_utils_extended/simulate.py
alembic_utils_extended/statement.py
alembic_utils_extended/testbase.py
alembic_utils_extended-1.0.1.dist-info/LICENSE
alembic_utils_extended-1.0.1.dist-info/METADATA
alembic_utils_extended-1.0.1.dist-info/WHEEL
alembic_utils_extended-1.0.1.dist-info/RECORD
