Metadata-Version: 2.3
Name: alembic-utils-extended
Version: 1.0.1
Summary: A sqlalchemy/alembic extension for migrating entities like functions, triggers, views, and materialized views.
License: MIT
Author: Justin Malin
Author-email: justin@joincandidhealth.com
Requires-Python: >=3.10
Classifier: Development Status :: 4 - Beta
Classifier: License :: OSI Approved :: MIT License
Classifier: Intended Audience :: Developers
Classifier: Programming Language :: Python :: 3
Classifier: Programming Language :: Python :: 3.10
Classifier: Programming Language :: Python :: 3.11
Classifier: Programming Language :: Python :: 3.12
Classifier: Programming Language :: Python :: 3.13
Classifier: Programming Language :: SQL
Requires-Dist: alembic (>=1.9)
Requires-Dist: flupy
Requires-Dist: parse (>=1.8.4)
Requires-Dist: sqlalchemy (>=1.4)
Requires-Dist: typing_extensions (>=0.1.0)
Project-URL: GitHub, https://github.com/candidhealth/alembic-utils-extended
Project-URL: PyPI, https://pypi.org/project/alembic-utils/
